oot/__init__.py
oot/loaders.py
oot/m_exceptions.py
oot/main.py
oot/parser.py
oot/schema_validator.py
oot-0.1.0.3.dist-info/LICENSE
oot-0.1.0.3.dist-info/METADATA
oot-0.1.0.3.dist-info/WHEEL
oot-0.1.0.3.dist-info/RECORD
