Metadata-Version: 2.1
Name: oot
Version: 0.1.0.3
Summary: Order of the Template: A Python package for parsing Jinja templates and YAML files with environment variables.
License: MIT
Author: Elsayed91
Author-email: elsayed.is@outlook.com
Requires-Python: >=3.9,<4.0
Classifier: License :: OSI Approved :: MIT License
Classifier: Programming Language :: Python :: 3
Classifier: Programming Language :: Python :: 3.9
Classifier: Programming Language :: Python :: 3.10
Classifier: Programming Language :: Python :: 3.11
Requires-Dist: fastjsonschema (>=2.18.0,<3.0.0)
Requires-Dist: jinja2 (>=3.1.2,<4.0.0)
Requires-Dist: jsonschema (>=4.18.4,<5.0.0)
Requires-Dist: pyyaml (>=6.0.1,<7.0.0)
